[
  {
    "id": "user-001",
    "authId": "c18d6a34-31cc-48d6-b93b-5155c9a9d884",
    "email": "loremipsum@gmail.com",
    "name": "Lorem Ipsum",
    "avatar": "https://api.dicebear.com/9.x/bottts/svg?seed=nicotinom",
    "createdAt": 1763733906974,
    "updatedAt": 1763733906974
  },
  {
    "id": "usr-l7c",
    "authId": "cea73346-7b32-4f91-8808P-995ee32939bd",
    "name": "Isabella Wunsch",
    "avatar": "https://api.dicebear.com/9.x/bottts/svg?seed=Isabella",
    "email": "Isabella_Wunsch97@hotmail.com",
    "createdAt": 1758208525655,
    "updatedAt": 1762863822284
  },
  {
    "id": "usr-tol",
    "authId": "Jr3oJbawwDQIBIkmeiD5qquqjqTWvC",
    "name": "Maurine Farrell",
    "avatar": "https://api.dicebear.com/9.x/micah/svg?seed=MaurineFarrell",
    "email": "Maurine_Farrell@hotmail.com",
    "createdAt": 1631996540774,
    "updatedAt": 1676241776442
  },
  {
    "id": "usr-PBx",
    "authId": "lipGSvFACFQ5Lfcz5SCI1Ay99HjGyo",
    "name": "Haskell Friesen",
    "avatar": "https://api.dicebear.com/9.x/bottts/svg?seed=HaskellFriesen",
    "email": "Haskell_Friesen@hotmail.com",
    "createdAt": 1759640722393,
    "updatedAt": 1769576729259
  },
  {
    "id": "usr-AG9",
    "authId": "oelvF68jFQyQnjlaPkyzw0ZUciwTYf",
    "name": "Flo Haag",
    "avatar": "https://api.dicebear.com/9.x/micah/svg?seed=FloHaag",
    "email": "Flo_Haag99@hotmail.com",
    "createdAt": 1702753965679,
    "updatedAt": 1758186150942
  },
  {
    "id": "usr-crx",
    "authId": "5iVzsKJ3HQaMhjF6FTHrrLz5AOkVKz",
    "name": "Godfrey Crooks",
    "avatar": "https://api.dicebear.com/9.x/adventurer/svg?seed=GodfreyCrooks",
    "email": "Godfrey_Crooks98@hotmail.com",
    "createdAt": 1732285055757,
    "updatedAt": 1735384590526
  },
  {
    "id": "usr-y7c",
    "authId": "OtO0yVAcInF1D1Kt7x4EZLz6HE3Nwq",
    "name": "Rylee Vandervort",
    "avatar": "https://api.dicebear.com/9.x/adventurer/svg?seed=RyleeVandervort",
    "email": "Rylee.Vandervort13@gmail.com",
    "createdAt": 1738047185102,
    "updatedAt": 1751793040408
  },
  {
    "id": "usr-UU5",
    "authId": "svj2e5eOT2iYxC0uZn6sXlNNcrIpbX",
    "name": "Jayden Hammes",
    "avatar": "https://api.dicebear.com/9.x/bottts/svg?seed=JaydenHammes",
    "email": "Jayden.Hammes@yahoo.com",
    "createdAt": 1716376149491,
    "updatedAt": 1764036749047
  },
  {
    "id": "usr-6ei",
    "authId": "Dhm0mxaBiD1T07M2IYSIXqSmV9WPQ7",
    "name": "Albina Kuvalis",
    "avatar": "https://api.dicebear.com/9.x/bottts/svg?seed=AlbinaKuvalis",
    "email": "Albina_Kuvalis23@gmail.com",
    "createdAt": 1707819885890,
    "updatedAt": 1708862873000
  },
  {
    "id": "usr-dzE",
    "authId": "ipsVAWyv0tVc3pnR1VGUBOkloKmfWU",
    "name": "Miracle Bogan",
    "avatar": "https://api.dicebear.com/9.x/adventurer/svg?seed=MiracleBogan",
    "email": "Miracle_Bogan@gmail.com",
    "createdAt": 1668764192809,
    "updatedAt": 1733929870383
  },
  {
    "id": "usr-qf7",
    "authId": "i95BmzbFdhJykxHUAeKMcOsMekXELG",
    "name": "Dorian Hauck",
    "avatar": "https://api.dicebear.com/9.x/micah/svg?seed=DorianHauck",
    "email": "Dorian_Hauck@gmail.com",
    "createdAt": 1645980505455,
    "updatedAt": 1705035623148
  },
  {
    "id": "usr-mdq",
    "authId": "dQshVjU2Hur22kWCmBcamRviWOkYZp",
    "name": "Rahul Abshire",
    "avatar": "https://api.dicebear.com/9.x/bottts/svg?seed=RahulAbshire",
    "email": "Rahul.Abshire94@gmail.com",
    "createdAt": 1717191786565,
    "updatedAt": 1739200113769
  },
  {
    "id": "usr-Crq",
    "authId": "nRh1URhw65PpFWf01HVsnxREeM8aBe",
    "name": "Desmond Gislason",
    "avatar": "https://api.dicebear.com/9.x/bottts/svg?seed=DesmondGislason",
    "email": "Desmond.Gislason@gmail.com",
    "createdAt": 1724895313031,
    "updatedAt": 1741165581995
  },
  {
    "id": "usr-JG3",
    "authId": "irhO8BZTd0YSVpKdoQ7TuqiUwNRVil",
    "name": "Drake Bauch-O'Connell",
    "avatar": "https://api.dicebear.com/9.x/adventurer/svg?seed=DrakeBauch-O'Connell",
    "email": "Drake_Bauch-OConnell23@gmail.com",
    "createdAt": 1707597080586,
    "updatedAt": 1735775075762
  },
  {
    "id": "usr-k9h",
    "authId": "Mw2YC3En8yJFfwxImNC2xRzavK6Oax",
    "name": "Torrance Kreiger",
    "avatar": "https://api.dicebear.com/9.x/bottts/svg?seed=TorranceKreiger",
    "email": "Torrance.Kreiger99@hotmail.com",
    "createdAt": 1674589864283,
    "updatedAt": 1698670559972
  },
  {
    "id": "usr-Nur",
    "authId": "jhXqSERQXHNJBII2vNfsqo7wrFy11H",
    "name": "Luz Rowe",
    "avatar": "https://api.dicebear.com/9.x/bottts/svg?seed=LuzRowe",
    "email": "Luz_Rowe52@hotmail.com",
    "createdAt": 1725337222425,
    "updatedAt": 1769598681502
  },
  {
    "id": "usr-btX",
    "authId": "19iWUaYKxVSoEEkbsgmXsGkZEc6WWC",
    "name": "Selmer Murazik",
    "avatar": "https://api.dicebear.com/9.x/adventurer/svg?seed=SelmerMurazik",
    "email": "Selmer.Murazik37@hotmail.com",
    "createdAt": 1616445051957,
    "updatedAt": 1651403135027
  },
  {
    "id": "usr-Oac",
    "authId": "ELOaZeAAXEAwL60XukmNnLrQ4tsgWU",
    "name": "Preston Kling",
    "avatar": "https://api.dicebear.com/9.x/micah/svg?seed=PrestonKling",
    "email": "Preston.Kling11@hotmail.com",
    "createdAt": 1683712096805,
    "updatedAt": 1692236271959
  },
  {
    "id": "usr-dBQ",
    "authId": "WhJ0S3JZvcACFaTC2Gc1yOR6FIiYh4",
    "name": "Cora Kuhic",
    "avatar": "https://api.dicebear.com/9.x/micah/svg?seed=CoraKuhic",
    "email": "Cora_Kuhic@hotmail.com",
    "createdAt": 1695645959184,
    "updatedAt": 1748274939499
  },
  {
    "id": "usr-LCv",
    "authId": "BKxTWUKfnhEkK7MAPqCyYKxaUcEWde",
    "name": "Deja Maggio",
    "avatar": "https://api.dicebear.com/9.x/adventurer/svg?seed=DejaMaggio",
    "email": "Deja_Maggio20@yahoo.com",
    "createdAt": 1748080637302,
    "updatedAt": 1767418958423
  },
  {
    "id": "usr-3kV",
    "authId": "WQ9qfcGuk6xlojoy0QVygZnHGqcX3u",
    "name": "Felipa Champlin",
    "avatar": "https://api.dicebear.com/9.x/bottts/svg?seed=FelipaChamplin",
    "email": "Felipa_Champlin@yahoo.com",
    "createdAt": 1648570650457,
    "updatedAt": 1684692775428
  },
  {
    "id": "usr-5Ip",
    "authId": "UjWvlEfecXuKtAAYFe0dsoOM5XwApE",
    "name": "Rhiannon Boehm",
    "avatar": "https://api.dicebear.com/9.x/micah/svg?seed=RhiannonBoehm",
    "email": "Rhiannon_Boehm97@gmail.com",
    "createdAt": 1751156563024,
    "updatedAt": 1764830231370
  },
  {
    "id": "usr-C6A",
    "authId": "te1mCkjKLI6wyKTmqJFylcb55Qn3Td",
    "name": "Waldo Schuster",
    "avatar": "https://api.dicebear.com/9.x/micah/svg?seed=WaldoSchuster",
    "email": "Waldo_Schuster65@gmail.com",
    "createdAt": 1656043692262,
    "updatedAt": 1678489159189
  },
  {
    "id": "usr-HsR",
    "authId": "HTKwus1xq97r2Znn3q01lOs0aJJKll",
    "name": "Vivian Reichert",
    "avatar": "https://api.dicebear.com/9.x/micah/svg?seed=VivianReichert",
    "email": "Vivian_Reichert85@yahoo.com",
    "createdAt": 1740237122736,
    "updatedAt": 1752662492394
  },
  {
    "id": "usr-mfl",
    "authId": "lD0LpqtrulspwCevA1wepPkt1jDjci",
    "name": "Monica Hickle",
    "avatar": "https://api.dicebear.com/9.x/micah/svg?seed=MonicaHickle",
    "email": "Monica.Hickle88@gmail.com",
    "createdAt": 1764252202823,
    "updatedAt": 1764876622975
  },
  {
    "id": "usr-0i5",
    "authId": "uhDu2juz6ElbN4VHt0oERCorSl4rZn",
    "name": "Jalyn Lind",
    "avatar": "https://api.dicebear.com/9.x/adventurer/svg?seed=JalynLind",
    "email": "Jalyn_Lind@gmail.com",
    "createdAt": 1644206699893,
    "updatedAt": 1649949019321
  },
  {
    "id": "usr-wGj",
    "authId": "FiTS49H0OmK2c4bnuUCH5hZyM2560V",
    "name": "Cecilia Marvin",
    "avatar": "https://api.dicebear.com/9.x/bottts/svg?seed=CeciliaMarvin",
    "email": "Cecilia.Marvin93@hotmail.com",
    "createdAt": 1653759044029,
    "updatedAt": 1771042064421
  },
  {
    "id": "usr-A4d",
    "authId": "Wuzgr8w32G3wgbzis8764yKNXa8tRL",
    "name": "Myron Zemlak",
    "avatar": "https://api.dicebear.com/9.x/bottts/svg?seed=MyronZemlak",
    "email": "Myron.Zemlak@yahoo.com",
    "createdAt": 1701779355905,
    "updatedAt": 1712701893586
  },
  {
    "id": "usr-kpq",
    "authId": "7nvIzpVBYRFTZdGU1N5UBa2P8W5PqS",
    "name": "Giovanny Hintz",
    "avatar": "https://api.dicebear.com/9.x/bottts/svg?seed=GiovannyHintz",
    "email": "Giovanny_Hintz@gmail.com",
    "createdAt": 1734954618035,
    "updatedAt": 1766077328194
  },
  {
    "id": "usr-10G",
    "authId": "64uIYi74c60ha1lPiIJ1X8InRZbOvX",
    "name": "Janick Hamill",
    "avatar": "https://api.dicebear.com/9.x/adventurer/svg?seed=JanickHamill",
    "email": "Janick.Hamill0@gmail.com",
    "createdAt": 1717533304817,
    "updatedAt": 1749516259529
  },
  {
    "id": "usr-uVM",
    "authId": "f6QKRnusjkIKRQKkIYUY2BdfQKkwb0",
    "name": "Daphnee Green",
    "avatar": "https://api.dicebear.com/9.x/adventurer/svg?seed=DaphneeGreen",
    "email": "Daphnee_Green@yahoo.com",
    "createdAt": 1755671225769,
    "updatedAt": 1766865554178
  },
  {
    "id": "usr-7eW",
    "authId": "dLBpA8uYqfVBJx0KYIOQZhrx9thPl5",
    "name": "Junior Jones",
    "avatar": "https://api.dicebear.com/9.x/adventurer/svg?seed=JuniorJones",
    "email": "Junior.Jones15@hotmail.com",
    "createdAt": 1615356101205,
    "updatedAt": 1749678102823
  },
  {
    "id": "usr-JbD",
    "authId": "KbdHNXjy9rglNNH7hWsC1wG37mWf1O",
    "name": "Ryder Bins",
    "avatar": "https://api.dicebear.com/9.x/bottts/svg?seed=RyderBins",
    "email": "Ryder.Bins86@hotmail.com",
    "createdAt": 1747675315625,
    "updatedAt": 1760432845012
  },
  {
    "id": "usr-GFa",
    "authId": "PUojzYIMLXOgefdcVX53Ryds4Y8OXI",
    "name": "Sister Goodwin",
    "avatar": "https://api.dicebear.com/9.x/bottts/svg?seed=SisterGoodwin",
    "email": "Sister_Goodwin@gmail.com",
    "createdAt": 1627728549903,
    "updatedAt": 1712519587972
  },
  {
    "id": "usr-Fzl",
    "authId": "pNmYU4QF3XPPUVdW2SsPgKN5UOAHlt",
    "name": "Braxton Pacocha",
    "avatar": "https://api.dicebear.com/9.x/bottts/svg?seed=BraxtonPacocha",
    "email": "Braxton.Pacocha@yahoo.com",
    "createdAt": 1637002003872,
    "updatedAt": 1704211453276
  },
  {
    "id": "usr-vn5",
    "authId": "P0lkUrT5QBxiugsLCGT3cIpETJV9KH",
    "name": "Otilia Collier",
    "avatar": "https://api.dicebear.com/9.x/micah/svg?seed=OtiliaCollier",
    "email": "Otilia_Collier@yahoo.com",
    "createdAt": 1614956748117,
    "updatedAt": 1621681929024
  },
  {
    "id": "usr-Qmw",
    "authId": "u8mZysygzJ6hcKWqD18nFDb8Wms5UF",
    "name": "Alexis Sanford",
    "avatar": "https://api.dicebear.com/9.x/bottts/svg?seed=AlexisSanford",
    "email": "Alexis.Sanford@hotmail.com",
    "createdAt": 1694178053057,
    "updatedAt": 1727500999023
  },
  {
    "id": "usr-xwR",
    "authId": "RQHogX2CQgYScgT6bB9zzAfOYhRilM",
    "name": "Amelie Steuber",
    "avatar": "https://api.dicebear.com/9.x/adventurer/svg?seed=AmelieSteuber",
    "email": "Amelie.Steuber18@hotmail.com",
    "createdAt": 1635420042109,
    "updatedAt": 1643827466060
  },
  {
    "id": "usr-Zjx",
    "authId": "NelcnJIbtGJDcRhmyREHdl8JWJ7Gq5",
    "name": "Gertrude Block",
    "avatar": "https://api.dicebear.com/9.x/bottts/svg?seed=GertrudeBlock",
    "email": "Gertrude.Block@hotmail.com",
    "createdAt": 1771362919006,
    "updatedAt": 1771422958663
  },
  {
    "id": "usr-t74",
    "authId": "FPVoWOqpk40ffJ9GJs7IUmLJ33FPV8",
    "name": "Lilyan Hane",
    "avatar": "https://api.dicebear.com/9.x/adventurer/svg?seed=LilyanHane",
    "email": "Lilyan.Hane@yahoo.com",
    "createdAt": 1705754799806,
    "updatedAt": 1724283158347
  },
  {
    "id": "usr-8AP",
    "authId": "LS2GcyMqHQWxjoReS3Y7SxyYWNEG8s",
    "name": "Dameon Jerde",
    "avatar": "https://api.dicebear.com/9.x/micah/svg?seed=DameonJerde",
    "email": "Dameon_Jerde@hotmail.com",
    "createdAt": 1681436695363,
    "updatedAt": 1690609447753
  },
  {
    "id": "usr-aO1",
    "authId": "UkV3jAW5OCDZjmxCjH5c0KWLahFjpf",
    "name": "Aditya Rippin",
    "avatar": "https://api.dicebear.com/9.x/bottts/svg?seed=AdityaRippin",
    "email": "Aditya.Rippin@hotmail.com",
    "createdAt": 1698002706089,
    "updatedAt": 1761859763124
  },
  {
    "id": "usr-TPo",
    "authId": "OQh76SuFoMPTDTRgAgDTtP1RWjHO7p",
    "name": "Dawson Ondricka",
    "avatar": "https://api.dicebear.com/9.x/bottts/svg?seed=DawsonOndricka",
    "email": "Dawson.Ondricka@gmail.com",
    "createdAt": 1646339903718,
    "updatedAt": 1739738847899
  },
  {
    "id": "usr-Wk7",
    "authId": "wTM9ieVhasB915EagFSXneJIY6SaKZ",
    "name": "Gust Gislason",
    "avatar": "https://api.dicebear.com/9.x/bottts/svg?seed=GustGislason",
    "email": "Gust.Gislason53@gmail.com",
    "createdAt": 1650312656991,
    "updatedAt": 1740215252334
  },
  {
    "id": "usr-Mgv",
    "authId": "8ABd4HDtTYJX99ZnyWBRHRtW7OeCMH",
    "name": "Ona Waelchi",
    "avatar": "https://api.dicebear.com/9.x/bottts/svg?seed=OnaWaelchi",
    "email": "Ona.Waelchi29@gmail.com",
    "createdAt": 1683082841028,
    "updatedAt": 1765291191171
  },
  {
    "id": "usr-aOk",
    "authId": "zBUzRqEbIVqEx0UOp5lwfPicaJxHio",
    "name": "Carolyne Fritsch",
    "avatar": "https://api.dicebear.com/9.x/micah/svg?seed=CarolyneFritsch",
    "email": "Carolyne.Fritsch@yahoo.com",
    "createdAt": 1754985186251,
    "updatedAt": 1760423824216
  },
  {
    "id": "usr-sgM",
    "authId": "xkVYbYASi20q0rKFJAXeUY0qFCZECV",
    "name": "Stevie Aufderhar-Kunde",
    "avatar": "https://api.dicebear.com/9.x/adventurer/svg?seed=StevieAufderhar-Kunde",
    "email": "Stevie.Aufderhar-Kunde35@hotmail.com",
    "createdAt": 1756011235201,
    "updatedAt": 1768886558990
  },
  {
    "id": "usr-g8t",
    "authId": "FBB5ucIyBAi5pizddkaoPQ6kCeVHd6",
    "name": "Hadley Will",
    "avatar": "https://api.dicebear.com/9.x/micah/svg?seed=HadleyWill",
    "email": "Hadley.Will@gmail.com",
    "createdAt": 1625398809477,
    "updatedAt": 1652851863966
  },
  {
    "id": "usr-qiI",
    "authId": "NPLGbJhI6qo2SFMFlv7akDBMwF2VQW",
    "name": "Gonzalo Connelly",
    "avatar": "https://api.dicebear.com/9.x/adventurer/svg?seed=GonzaloConnelly",
    "email": "Gonzalo_Connelly33@gmail.com",
    "createdAt": 1641143027630,
    "updatedAt": 1660163762909
  },
  {
    "id": "usr-5D6",
    "authId": "1RfsWCnQduzA1nvsOIVd9cEfFG5Jjd",
    "name": "Kamron Ritchie",
    "avatar": "https://api.dicebear.com/9.x/adventurer/svg?seed=KamronRitchie",
    "email": "Kamron.Ritchie@gmail.com",
    "createdAt": 1654575299556,
    "updatedAt": 1759325983035
  },
  {
    "id": "usr-J7O",
    "authId": "FX1811QDDn3q9VSi11wPlERD0yaNpr",
    "name": "Leland Emmerich",
    "avatar": "https://api.dicebear.com/9.x/bottts/svg?seed=LelandEmmerich",
    "email": "Leland_Emmerich@hotmail.com",
    "createdAt": 1661686256867,
    "updatedAt": 1686882159008
  },
  {
    "id": "usr-7HW",
    "authId": "uuIcmjZaashRrGOgJofTzubTDW27Ss",
    "name": "Carol Lind",
    "avatar": "https://api.dicebear.com/9.x/micah/svg?seed=CarolLind",
    "email": "Carol.Lind@yahoo.com",
    "createdAt": 1687398925908,
    "updatedAt": 1706165015111
  }
]